<?xml version="1.0" encoding="UTF-8" ?> 
<Module>
	<ModulePrefs title="Gadget Testing" height="120">
		<Require feature="wave" /> 
	</ModulePrefs>
	<Content type="html">
    <![CDATA[ 
			<style>
			
				#content_div {
					height: 80px; 
					width: 80px; 
				}
				
				.gadget_table {
					border: solid black 1px;
					font-size: 0.8em;
				}

				.gadget_table td, .gadget_table th {
					border: solid black 1px;
				}
				
			</style>
      <div id="content_div">
				<table class="gadget_table">
					<tr><th>Participant</th><th>Choice</th></tr>
					<tr><th>You</th><th>Yes</th></tr>
					<tr><th>Me</th><th>No</th></tr>
					<tr><th>Him</th><th>Maybe</th></tr>
				</table>
				<form style="clear: both; display: block;">
					<input type="radio" name="choice" value="Yes"/> Yes<br/>
					<input type="radio" name="choice" value="No"/> No<br/>
					<input type="radio" name="choice" value="Maybe"/> Maybe<br/>
				</form>
			</div>
    ]]>
    </Content>
</Module>